CHANGES.rst
CONTRIBUTORS.rst
DEVELOP.rst
LICENSE.GPL
LICENSE.rst
MANIFEST.in
README.rst
setup.cfg
setup.py
docs/conf.py
docs/index.rst
src/derico/__init__.py
src/derico.article.egg-info/PKG-INFO
src/derico.article.egg-info/SOURCES.txt
src/derico.article.egg-info/dependency_links.txt
src/derico.article.egg-info/entry_points.txt
src/derico.article.egg-info/namespace_packages.txt
src/derico.article.egg-info/not-zip-safe
src/derico.article.egg-info/requires.txt
src/derico.article.egg-info/top_level.txt
src/derico/article/__init__.py
src/derico/article/configure.zcml
src/derico/article/interfaces.py
src/derico/article/permissions.zcml
src/derico/article/setuphandlers.py
src/derico/article/testing.py
src/derico/article/browser/__init__.py
src/derico/article/browser/configure.zcml
src/derico/article/browser/overrides/.gitkeep
src/derico/article/browser/static/.gitkeep
src/derico/article/content/__init__.py
src/derico/article/content/article_page.py
src/derico/article/locales/README.rst
src/derico/article/locales/__init__.py
src/derico/article/locales/derico.article.pot
src/derico/article/locales/update.py
src/derico/article/locales/update.sh
src/derico/article/locales/en/LC_MESSAGES/derico.article.po
src/derico/article/profiles/default/browserlayer.xml
src/derico/article/profiles/default/catalog.xml
src/derico/article/profiles/default/metadata.xml
src/derico/article/profiles/default/rolemap.xml
src/derico/article/profiles/default/types.xml
src/derico/article/profiles/default/registry/main.xml
src/derico/article/profiles/default/types/ArticlePage.xml
src/derico/article/profiles/uninstall/browserlayer.xml
src/derico/article/tests/__init__.py
src/derico/article/tests/test_ct_article_page.py
src/derico/article/tests/test_robot.py
src/derico/article/tests/test_setup.py
src/derico/article/tests/robot/test_ct_article_page.robot
src/derico/article/tests/robot/test_example.robot